{"trial_id": "0197", "hyperparameters": {"space": [{"class_name": "Int", "config": {"name": "num_filters", "default": 50, "conditions": [], "min_value": 50, "max_value": 100, "step": 10, "sampling": "linear"}}, {"class_name": "Int", "config": {"name": "dense", "default": 256, "conditions": [], "min_value": 4, "max_value": 640, "step": 32, "sampling": "linear"}}, {"class_name": "Float", "config": {"name": "dropout-2", "default": 0.0, "conditions": [], "min_value": 0.0, "max_value": 0.5, "step": 0.05, "sampling": "linear"}}], "values": {"num_filters": 70, "dense": 36, "dropout-2": 0.25, "tuner/epochs": 23, "tuner/initial_epoch": 8, "tuner/bracket": 3, "tuner/round": 1, "tuner/trial_id": "0154"}}, "metrics": {"metrics": {"loss": {"direction": "min", "observations": [{"value": [0.15668480098247528], "step": 14}]}, "mse": {"direction": "min", "observations": [{"value": [0.15668480098247528], "step": 14}]}, "mae": {"direction": "min", "observations": [{"value": [0.2840261161327362], "step": 14}]}, "val_loss": {"direction": "min", "observations": [{"value": [0.14156922698020935], "step": 14}]}, "val_mse": {"direction": "min", "observations": [{"value": [0.14156922698020935], "step": 14}]}, "val_mae": {"direction": "min", "observations": [{"value": [0.27954337000846863], "step": 14}]}}}, "score": 0.14156922698020935, "best_step": 14, "status": "COMPLETED", "message": null}